Workbook
Name _15_ago_95: #REF!
Name _15_ago_95: #REF!
Name JUNUIO_11: #REF!
Name JUNUIO_11: #REF!
Name por_credito: '[1]Flujo de Caja'!$Z$10
Name por_credito: '[2]Flujo de Caja'!$Z$10

Sheet PLAN DE NEGOCIOS 15%
B1: Thorne 1280 | F1: 44677
A2: 1 | B2: ESTUDIO DE PREFACTIBILIDAD
A4: TERRENO | D4: viviendas | E4: Exteriores | F4: cocheras PB | G4: cocheras SS
D5: (cubierta 100% + semicub 50%) | E5: vendibles
A6: UBICACIÓN
B7: Superficie del Terreno (por título) | C7: 735
B8: FOT | C8: 3.4 | D8: 3607
B9: Superficie Edificable PROPIA | D9: 3607 | E9: 300 | F9: 601 | G9: =+C7 -> 735
B10: n° de cocheras | F10: 18 | G10: 26
A12: DISTRIBUCIÓN
B13: Superficie COMÚN cubiertas | C13: =D13/D9 -> 0.23593014 | D13: 851
B14: Superficie cubierta TOTAL (CUB + SEMICUB) | D14: =+D13+D9 -> 4458 | E14: =E13+E9 -> 300 | F14: =+F9 -> 601 | G14: =+G9 -> 735
B15: Superficie TOTAL DEL PROYECTO | D15: =SUM(D14:G14) -> 6094
I16: GMPEM
A17: TERRENO | I17: Gasto minimo de puesta en marcha
A19: CASH POR EL TERRENO | D19: 150000 | I19: 1 | J19: =+I19*D19 -> 150000
A21: M2 POR EL TERRENO | C21: 0.15 | D21: =+D9*$C$21 -> 541.05 | E21: =+E9*$C$21 -> 45 | F21: 2 | G21: 3
C22: }
A23: Valor futuro de los m2 | D23: =+D21*D68 -> 1217362.5 | E23: =+E21*E68 -> 33750 | F23: =+F21*F68 -> 50000 | G23: =+G21*G68 -> 66000
A25: PRECIO DEL TERRENO | D25: =SUM(D23:G23)+D19 -> 1517112.5
A27: Inc. de la tierra u$s/m2 vendibles | D27: =+(D25+D46)/(D9+E9) -> 420.3001 | F27: SE DESPRECIAN LOS EXTERIORES
A29: M2 vendibles para el emprendimiento | D29: =D9-D21 -> 3065.95 | E29: =E9-E21 -> 255 | F29: =F10-F21 -> 16 | G29: =G10-G21 -> 23
A31: COSTOS OBRA | D31: =+D4 -> viviendas | E31: =+E4 -> Exteriores | F31: =+F4 -> cocheras PB | G31: =+G4 -> cocheras SS
B32: m2 de construccion | D32: =D14 -> 4458 | E32: =E14 -> 300 | F32: =F14 -> 601 | G32: =G14 -> 735
B33: Costo en u$s/m2 | D33: 750 | E33: 200 | F33: 500 | G33: 500
B34: Costo por Sector | D34: =+D32*D33 -> 3343500 | E34: =+E32*E33 -> 60000 | F34: =+F32*F33 -> 300500 | G34: =+G32*G33 -> 367500
B35: Costo total de obra | D35: =SUM(D34:G34) -> 4071500 | I35: 0.15 | J35: =+I35*D35 -> 610725
B36: Costos Blandos: de obra proyecto direccion y gerenciamiento, asesores, desarrollo | J36: =+I36*D36 -> 0
B37: Proyecto | C37: 0.03 | D37: =C37*$D$35 -> 122145 | I37: 0.15 | J37: =+I37*D37 -> 18321.75
B38: Dirección | C38: 0.03 | D38: =C38*$D$35-D85 -> 122145 | J38: =+I38*D38 -> 0
B39: Gerenciamiento | C39: 0.02 | D39: =C39*$D$35 -> 81430 | I39: 0.1 | J39: =+I39*D39 -> 8143
B40: Asesores | C40: 0.015 | D40: =C40*$D$35 -> 61072.5 | I40: 0.2 | J40: =+I40*D40 -> 12214.5
B41: Administracion | C41: 0.015 | D41: =SUM(D35:D40)*C41 -> 66874.387 | I41: 0.05 | J41: =+I41*D41 -> 3343.7194
B42: Desarrollo | C42: 0.04 | D42: =SUM(D35:D41)*C42 -> 181006.68 | I42: 0.1 | J42: =+I42*D42 -> 18100.668
B43: Costos Indirectos | C43: =+D43/D35 -> 0.155882 | D43: =SUM(D37:D42) -> 634673.56 | J43: =+I43*D43 -> 0
B44: comision inmobiliaria por compra de la tierra | C44: 0.04 | D44: =+C44*D25 -> 60684.5 | I44: 1 | J44: =+I44*D44 -> 60684.5
B45: escrituracion / conformacio SA, est | C45: gl | D45: 15000 | E45: VERFICAR en cada caso | I45: 1 | J45: =+I45*D45 -> 15000
B46: Plusvalia por el terreno | C46: gl | D46: 125000 | E46: Ver pestaña PLUSVALIA | I46: 1 | J46: =+I46*D46 -> 125000
B47: Derechos de construcción U$S/m2 | C47: 10 | D47: =+C47*D15 -> 60940 | E47: VERFICAR en cada caso | I47: 1 | J47: =+I47*D47 -> 60940
B48: Marketing y promocion | C48: 0.015 | D48: =+(D35+D43)*C48 -> 70592.603 | I48: 0.3 | J48: =+I48*D48 -> 21177.781
B49: Costos de ventas , administracion y legales | C49: =+D49/(D35+D43) -> 0.070591766 | D49: =SUM(D44:D48) -> 332217.1 | J49: =SUM(J18:J48) -> 1103650.9
B50: IVA promedio | C50: 0.12 | D50: =+(D35+D43+D49)*C50 -> 604606.88 | I50: =+C50 -> 0.12 | J50: =+J49*I50 -> 132438.11
A51: PARCIAL COSTOS OBRA | D51: =+D35+D43+D49+D50 -> 5642997.5 | I51: GMPEM | J51: =+J49+J50 -> 1236089
A52: =+A19 -> CASH POR EL TERRENO | D52: =+D19 -> 150000
A53: COSTO TOTAL (Obra + Cash x Terreno + varios) | D53: =+D51+D52 -> 5792997.5
A56: INDICADORES | D56: U$S/m2
A57: INCIDENCIA | D57: =+D27 -> 420.3001
A58: COSTO TOTAL (propio + comun + cochera) SIN TERRENO | D58: =+D53/D15 -> 950.60675
A59: COSTO TOTAL (propio + comun + cochera) CON TERRENO | D59: =+D53/D67 -> 1889.4625 | E59: se desprecian los exteriores
A60: COSTO TOTAL (propio + comun + cochera) CON TERRENO + COSTO DE VENTAS | D60: =+(F110+F111)/D67 -> 2091.6035 | E60: se desprecian los exteriores
A62: =+B13 -> Superficie COMÚN cubiertas | D62: =+C13 -> 0.23593014
A63: Cocheras | C63: m2 por cochera | D63: =+(F9+G9)/(F10+G10) -> 30.363636
A66: VENTAS
B67: m2 estimado para venta | C67: 0.98 | D67: =+D29 -> 3065.95 | E67: =+E29 -> 255 | F67: =+F29 -> 16 | G67: =+G29 -> 23
B68: Precio venta | D68: 2250 | E68: =+D68/3 -> 750 | F68: 25000 | G68: 22000
B69: Parcial Ventas | D69: =+D67*D68 -> 6898387.5 | E69: =+E67*E68 -> 191250 | F69: =+F67*F68 -> 400000 | G69: =+G67*G68 -> 506000
B70: Total ventas | D70: =SUM(D69:G69) -> 7995637.5
B71: GASTOS VENTAS
B72: Gastos comercializacion (comisiones) | C72: 0.02 | D72: =D70*$C$72 -> 159912.75
B73: Gastos escrituración retencion + ICHeque + IIGG | C73: =(3%+3.5%+1.2%) -> 0.077 | D73: =D70*$C$73 -> 615664.09
B74: IVA a pagar | D74: =+D104 -> -5822.7499
B75: Total gastos de Ventas | C75: =+D75/D70 -> 0.096271759 | D75: =SUM(D72:D74) -> 769754.09
A77: SALDOS
B78: VENTAS | D78: =+D70 -> 7995637.5
B79: COSTO DIRECTO | D79: =+D53 -> 5792997.5
B80: COSTO DE VENTAS | D80: =+D75 -> 769754.09
A82: SALDO parcial de VENTAS | D82: =+D78-D79-D80 -> 1432885.9
C83: m2
B84: =+B44 -> comision inmobiliaria por compra de la tierra | D84: =+C84*$D$68 -> 0
B85: m2 por P+DDO+G | C85: 0 | D85: =+C85*$D$68 -> 0
B86: m2 / Fee por desarrollo del negocio | D86: =+C86*$D$68 -> 0
A87: SALDO VENTAS | D87: =+D82-D84-D85-D86 -> 1432885.9
A88: % RENTABILIDAD | D88: =+D87/D53 -> 0.24734792
B90: CALCULO IVA A PAGAR
B92: IVA COSTOS
B93: =+A53 -> COSTO TOTAL (Obra + Cash x Terreno + varios) | D93: =SUM(D94:D95) -> 7160110
B94: COSTO OBRA | C94: =+D94/D93 -> 0.78811604 | D94: =D51 -> 5642997.5
B95: TIERRA | C95: =+D95/D93 -> 0.21188396 | D95: =+D25 -> 1517112.5
B97: IVA VENTAS
B98: =+B70 -> Total ventas | D98: =+D70 -> 7995637.5
B99: % CONSTRUCCION (sujeto a IVA) | C99: =+C94 -> 0.78811604 | D99: =+D98*C99 -> 6301490.1
B100: % TIERRA (no sujeto a IVA) | C100: =+C95 -> 0.21188396 | D100: =+D98*C100 -> 1694147.4
B102: IVA VENTAS ( a la construccion) | C102: 0.105 | D102: =+D99/(1+C102)*C102 -> 598784.13
B103: IVA COSTOS | D103: =+D50 -> 604606.88
B104: IVA A PAGAR | D104: =D102-D103 -> -5822.7499
A107: 2 | B107: PLAN DE NEGOCIOS
B109: Inversion | F109: U$S
B110: COSTOS OBRA | F110: =D51 -> 5642997.5
B111: COSTO DE VENTAS | F111: =D80 -> 769754.09
B112: CASH POR EL TERRENO | F112: =+D52 -> 150000
B113: Servicios de creditos / deuda | C113: Capital | E113: Intereses+ Gastos
B114: Total Inversion | F114: =SUM(F110:F113) -> 6562751.6
A116: VENTA
B117: preventa | C117: % venta | D117: Incremental | E117: viviendas | F117: local | G117: cocheras | H117: =+G4 -> cocheras SS | I117: Ingreso durante la obra | J117: Ingreso post entrega
B118: USD/m2 promedio | D118: -0.15 | E118: =+E123+(E123*D118) -> 1912.5 | F118: =+F123+(F123*D118) -> 637.5 | G118: =+G123+(G123*D118) -> 21250 | H118: =+H123+(H123*D118) -> 18700
B119: m2 para la venta | C119: 0.3 | E119: =$D$29*C119 -> 919.785 | G119: =$F$29*C119 -> 4.8 | H119: 0
B120: TOTAL PREVENTA | E120: =E119*E118 -> 1759088.8 | F120: =F119*F118 -> 0 | G120: =G119*G118 -> 102000 | H120: =H119*H118 -> 0 | I120: 1 | J120: =1-I120 -> 0
E121: =E120+F120+G120+H120 -> 1861088.8 | I121: =+I120*E121 -> 1861088.8 | J121: =+E121-I121 -> 0
B122: OBRA | E122: viviendas | F122: =+F117 -> local | G122: cocheras | H122: =+H117 -> cocheras SS
B123: USD/m2 promedio | C123: precio base | D123: 0 | E123: =+D68 -> 2250 | F123: =+E68 -> 750 | G123: =+F68 -> 25000 | H123: =+G68 -> 22000
...

Sheet Caso de Negocio
G1: 43561
B4: DATOS
D6: TOTALES | E6: TIERRA | G6: EMPRENDIMIENTO
B7: M2 vendibles (ponderados) | D7: =+DATOS!C5 -> 3907 | E7: =+'PLAN DE NEGOCIOS 15%'!D21+'PLAN DE NEGOCIOS 15%'!E21 -> 586.05 | G7: =+D7-E7 -> 3320.95
B8: =+DATOS!B6 -> n° cocheras | D8: =+DATOS!C6 -> 44 | E8: =+'PLAN DE NEGOCIOS 15%'!F21+'PLAN DE NEGOCIOS 15%'!G21 -> 5 | G8: =+D8-E8 -> 39
B9: Total m2 cubiertos | D9: =+DATOS!C7 -> 6094
B12: =+DATOS!B20 -> valor de venta m2 (promedio) | D12: =+DATOS!C20 -> 2250 | E12: valor actual | G12: 2800
B13: =+DATOS!B21 -> valor de venta cocheras (promedio) | D13: =+DATOS!C21 -> 25000
B15: CASO DE NEGOCIOS | G15: U$S MM
B17: INVERSION | F17: =SUM(C18:C24) -> 6562751.6 | G17: =F17/1000000 -> 6.5627516
B18: CASH POR EL TERRENO | C18: =+'PLAN DE NEGOCIOS 15%'!D19 -> 150000 | D18: =+C18/$F$17 -> 0.022856266 | E18: 15% de los m2 + 5 cocheras | G18: =+'PLAN DE NEGOCIOS 15%'!D19 -> 150000
B19: COSTOS OBRA | C19: =+'PLAN DE NEGOCIOS 15%'!D35 -> 4071500 | D19: =+C19/$F$17 -> 0.62039526 | G19: =+C19/1000000 -> 4.0715
B20: Indirectos | C20: =+'PLAN DE NEGOCIOS 15%'!D43 -> 634673.56 | D20: =+C20/$F$17 -> 0.096708454 | G20: =+C20/1000000 -> 0.63467356
B21: Total gastos de Ventas | C21: =+'PLAN DE NEGOCIOS 15%'!D49 -> 332217.1 | D21: =+C21/$F$17 -> 0.050621618 | G21: =+C21/1000000 -> 0.3322171
B22: IVA | C22: =+'PLAN DE NEGOCIOS 15%'!D50 -> 604606.88 | D22: =+C22/$F$17 -> 0.09212704 | G22: =+C22/1000000 -> 0.60460688
B23: SERVICIOS DE CREDITOS | C23: 0 | D23: =+C23/$F$17 -> 0 | G23: =+C23/1000000 -> 0
B24: =+'PLAN DE NEGOCIOS 15%'!B80 -> COSTO DE VENTAS | C24: =+'PLAN DE NEGOCIOS 15%'!D80 -> 769754.09 | D24: =+C24/$F$17 -> 0.11729136 | G24: =+C24/1000000 -> 0.76975409
B25: FINANCIAMIENTO | C25: (fondeo durante la obra) | F25: =SUM(F26:F30) -> 4962133 | G25: =F25/1000000 -> 4.962133
B26: Preventa | C26: =+'PLAN DE NEGOCIOS 15%'!I121 -> 1861088.8 | D26: =+'PLAN DE NEGOCIOS 15%'!E119 -> 919.785 | E26: m2 | F26: =+D27*C26 -> 1861088.8 | G26: =+F26/1000000 -> 1.8610888
D27: 1 | E27: cobrado durante la obra | G27: =+F27/1000000 -> 0
B28: Venta durante la obra | C28: =+'PLAN DE NEGOCIOS 15%'!E126 -> 2416316.2 | D28: =+'PLAN DE NEGOCIOS 15%'!E124 -> 919.785 | E28: =+E26 -> m2 | F28: =+D29*C28 -> 1812237.2 | G28: =+F28/1000000 -> 1.8122372
D29: 0.75 | E29: cobrado durante la obra | G29: =+F29/1000000 -> 0
B30: Venta remanente | C30: =+'PLAN DE NEGOCIOS 15%'!E131 -> 3682305.7 | D30: =+'PLAN DE NEGOCIOS 15%'!E129 -> 1226.38 | E30: =+E28 -> m2 | F30: =+'PLAN DE NEGOCIOS 15%'!I131 -> 1288807 | G30: =+F30/1000000 -> 1.288807
B31: INGRESOS FINANCIEROS / BANCO | C31: 0 | D31: =+'PLAN DE NEGOCIOS 15%'!I130 -> 0.35 | E31: =+E29 -> cobrado durante la obra
B32: CAPITAL PROPIO: (Inversion - Financiamiento) | F32: =+F17-F25 -> 1600618.6 | G32: =F32/1000000 -> 1.6006186
B34: INGRESOS REMANENTES | F34: =SUM(C35:C36) -> 2997577.8 | G34: =F34/1000000 -> 2.9975778
B35: Saldo Venta durante la obra | C35: =+C28-F28 -> 604079.06 | G35: =+C35/1000000 -> 0.60407906
B36: Venta Remanente | C36: =+C30-F30 -> 2393498.7 | G36: =+C36/1000000 -> 2.3934987
B37: Cancelacion ingresos financieros | G37: =+C37/1000000 -> 0
B38: RESULTADO DEL NEGOCIO | C38: Ingresos remanentes - Capital Propio) | F38: =+F34-F32 -> 1396959.2 | G38: =F38/1000000 -> 1.3969592
B39: Rentabilidad del negocio (resultado / inversión) | F39: =+G38/G17 -> 0.21286181
B40: Fee de exito desarrollador | C40: 0.2 | D40: =+C40*F38 -> 279391.84 | G40: =+D40/1000000 -> 0.27939184
B41: Socios Originantes | C41: 0.8 | D41: =+C41*F38 -> 1117567.3 | G41: =+D41/1000000 -> 1.1175673
B42: BENEFICIO SOCIOS ORIGINANTES | F42: =+D41 -> 1117567.3 | G42: =F42/1000000 -> 1.1175673
B43: Rentabilidad del capital | E43: =+F42/F32 -> 0.69820963 | G43: =+E43 -> 0.69820963
B45: =+DATOS!B29 -> PLAZOS
B46: =+DATOS!B30 -> Proyecto y tramitacion municial | G46: =+DATOS!C30 -> 12 meses
B47: =+DATOS!B31 -> Obra | G47: =+DATOS!C31 -> 36 meses
B48: =+DATOS!B32 -> post construccion | G48: =+DATOS!C32 -> 6 meses

Sheet DATOS
B2: DATOS | C2: 43561
B4: DATOS
B5: M2 vendibles | C5: =+'PLAN DE NEGOCIOS 15%'!D9+'PLAN DE NEGOCIOS 15%'!E9 -> 3907
B6: n° cocheras | C6: =+'PLAN DE NEGOCIOS 15%'!F10+'PLAN DE NEGOCIOS 15%'!G10 -> 44
B7: m2 totales cubiertos | C7: =+'PLAN DE NEGOCIOS 15%'!D15 -> 6094
B9: COSTO DEL TERRENO
B10: =+'PLAN DE NEGOCIOS 15%'!A19 -> CASH POR EL TERRENO | C10: =+'PLAN DE NEGOCIOS 15%'!D19 -> 150000
B11: M2 vendibles | C11: =+'PLAN DE NEGOCIOS 15%'!D21+'PLAN DE NEGOCIOS 15%'!E21 -> 586.05
B12: n° cocheras | C12: =+'PLAN DE NEGOCIOS 15%'!F21+'PLAN DE NEGOCIOS 15%'!G21 -> 5
B13: incidencia de la tierra | C13: =+C11/C5 -> 0.15
B15: COSTOS
B16: costo total de obra | C16: =+'PLAN DE NEGOCIOS 15%'!D51 -> 5642997.5
B17: costo total del emprendimento | C17: =+'PLAN DE NEGOCIOS 15%'!D53 -> 5792997.5
B19: VENTAS
B20: valor de venta m2 (promedio) | C20: =+'PLAN DE NEGOCIOS 15%'!D68 -> 2250
B21: valor de venta cocheras (promedio) | C21: =+'PLAN DE NEGOCIOS 15%'!F68 -> 25000
B22: valor de venta total | C22: =+'PLAN DE NEGOCIOS 15%'!D70 -> 7995637.5
B23: Total gastos de Ventas | C23: =+'PLAN DE NEGOCIOS 15%'!D80 -> 769754.09
B25: RESULTADOS
B26: Saldo | C26: =+'PLAN DE NEGOCIOS 15%'!D87 -> 1432885.9
B27: rentabilidad sobre venta | C27: =+'PLAN DE NEGOCIOS 15%'!D88 -> 0.24734792
B29: PLAZOS
B30: Proyecto y tramitacion municial | C30: 12 meses
B31: Obra | C31: 36 meses
B32: post construccion | C32: 6 meses
B36: ESCENARIOS
B37: =+'PLAN DE NEGOCIOS 15%'!B220 -> TOTAL PREVENTA | C37: =+'PLAN DE NEGOCIOS 15%'!C220 -> 0.2 | D37: =+'PLAN DE NEGOCIOS 15%'!D220 -> 0.2 | E37: =+'PLAN DE NEGOCIOS 15%'!E220 -> 0.3 | F37: =+'PLAN DE NEGOCIOS 15%'!F220 -> 0.3 | G37: =+'PLAN DE NEGOCIOS 15%'!G220 -> 0.4
B38: =+'PLAN DE NEGOCIOS 15%'!B221 -> TOTAL VENTA DURANTE LA OBRA | C38: =+'PLAN DE NEGOCIOS 15%'!C221 -> 0.2 | D38: =+'PLAN DE NEGOCIOS 15%'!D221 -> 0.3 | E38: =+'PLAN DE NEGOCIOS 15%'!E221 -> 0.3 | F38: =+'PLAN DE NEGOCIOS 15%'!F221 -> 0.4 | G38: =+'PLAN DE NEGOCIOS 15%'!G221 -> 0.4
B39: =+'PLAN DE NEGOCIOS 15%'!B222 -> TOTAL VENTA REMANENTE | C39: =+'PLAN DE NEGOCIOS 15%'!C222 -> 0.6 | D39: =+'PLAN DE NEGOCIOS 15%'!D222 -> 0.5 | E39: =+'PLAN DE NEGOCIOS 15%'!E222 -> 0.4 | F39: =+'PLAN DE NEGOCIOS 15%'!F222 -> 0.3 | G39: =+'PLAN DE NEGOCIOS 15%'!G222 -> 0.2
B40: =+'PLAN DE NEGOCIOS 15%'!B223 -> fondeo | C40: =+'PLAN DE NEGOCIOS 15%'!C223 -> 2074220.3 | D40: =+'PLAN DE NEGOCIOS 15%'!D223 -> 1804665.5 | E40: =+'PLAN DE NEGOCIOS 15%'!E223 -> 1600618.6 | F40: =+'PLAN DE NEGOCIOS 15%'!F223 -> 1230996.3 | G40: =+'PLAN DE NEGOCIOS 15%'!G223 -> 926881.75
B41: =+'PLAN DE NEGOCIOS 15%'!B224 -> reupero | C41: =+'PLAN DE NEGOCIOS 15%'!C224 -> 3945587.5 | D41: =+'PLAN DE NEGOCIOS 15%'!D224 -> 3559678.1 | E41: =+'PLAN DE NEGOCIOS 15%'!E224 -> 2997577.8 | F41: =+'PLAN DE NEGOCIOS 15%'!F224 -> 2593935.1 | G41: =+'PLAN DE NEGOCIOS 15%'!G224 -> 2014101.4
B42: =+'PLAN DE NEGOCIOS 15%'!B225 -> Beneficio Socios Originantes $ | C42: =+'PLAN DE NEGOCIOS 15%'!C225 -> 1403525.4 | D42: =+'PLAN DE NEGOCIOS 15%'!D225 -> 1316259.4 | E42: =+'PLAN DE NEGOCIOS 15%'!E225 -> 1047719.4 | F42: =+'PLAN DE NEGOCIOS 15%'!F225 -> 1022204.1 | G42: =+'PLAN DE NEGOCIOS 15%'!G225 -> 815414.76
B43: =+'PLAN DE NEGOCIOS 15%'!B226 -> Beneficio socios originantes % | C43: =+'PLAN DE NEGOCIOS 15%'!C226 -> 0.67665202 | D43: =+'PLAN DE NEGOCIOS 15%'!D226 -> 0.72936475 | E43: =+'PLAN DE NEGOCIOS 15%'!E226 -> 0.65457153 | F43: =+'PLAN DE NEGOCIOS 15%'!F226 -> 0.83038768 | G43: =+'PLAN DE NEGOCIOS 15%'!G226 -> 0.87973979
